{
  "sections": {
    "c735458c-9a43-4975-8226-cccaa1c52bc5": {
      "type": "hero",
      "settings": {
        "image": "shopify:\/\/shop_images\/mens-tshirts.jpg",
        "alignment": "center",
        "hero_layout": "full_width",
        "hero_size": "medium",
        "text_size": "medium",
        "title": "NEW ARRIVALS",
        "text": "",
        "button_label": "",
        "button_link": ""
      }
    },
    "collection": {
      "type": "collection",
      "settings": {
        "title": "PRODUCTS",
        "collection": "all-products",
        "grid": 4,
        "rows": 2,
        "show_vendor": false,
        "show_view_all": false
      }
    }
  },
  "order": [
    "c735458c-9a43-4975-8226-cccaa1c52bc5",
    "collection"
  ]
}
